glue_qt/__init__.py
glue_qt/_version.py
glue_qt/backends.py
glue_qt/config.py
glue_qt/conftest.py
glue_qt/logo.png
glue_qt/main.py
glue_qt/qglue.py
glue_qt/app/__init__.py
glue_qt/app/actions.py
glue_qt/app/application.py
glue_qt/app/application.ui
glue_qt/app/edit_subset_mode_toolbar.py
glue_qt/app/feedback.py
glue_qt/app/keyboard_shortcuts.py
glue_qt/app/layer_tree_widget.py
glue_qt/app/layer_tree_widget.ui
glue_qt/app/mdi_area.py
glue_qt/app/merge.ui
glue_qt/app/metadata.py
glue_qt/app/metadata.ui
glue_qt/app/plugin_manager.py
glue_qt/app/plugin_manager.ui
glue_qt/app/preferences.py
glue_qt/app/preferences.ui
glue_qt/app/report_crash.ui
glue_qt/app/report_feedback.ui
glue_qt/app/save_data.py
glue_qt/app/save_data.ui
glue_qt/app/splash_screen.py
glue_qt/app/terminal.py
glue_qt/app/versions.py
glue_qt/app/versions.ui
glue_qt/app/tests/__init__.py
glue_qt/app/tests/test_actions.py
glue_qt/app/tests/test_application.py
glue_qt/app/tests/test_edit_subset_mode_toolbar.py
glue_qt/app/tests/test_layer_tree_widget.py
glue_qt/app/tests/test_plugin_manager.py
glue_qt/app/tests/test_preferences.py
glue_qt/app/tests/test_save_data.py
glue_qt/app/tests/test_terminal.py
glue_qt/core/__init__.py
glue_qt/core/data_collection_model.py
glue_qt/core/dialogs.py
glue_qt/core/fitters.py
glue_qt/core/layer_artist_model.py
glue_qt/core/message_widget.py
glue_qt/core/message_widget.ui
glue_qt/core/mime.py
glue_qt/core/simpleforms.py
glue_qt/core/style_dialog.py
glue_qt/core/data_exporters/__init__.py
glue_qt/core/data_exporters/dialog.py
glue_qt/core/data_exporters/tests/__init__.py
glue_qt/core/data_exporters/tests/test_dialog.py
glue_qt/core/tests/__init__.py
glue_qt/core/tests/test_data_collection_model.py
glue_qt/core/tests/test_fitters.py
glue_qt/core/tests/test_layer_artist_model.py
glue_qt/core/tests/test_message_widget.py
glue_qt/core/tests/test_mime.py
glue_qt/core/tests/test_simpleforms.py
glue_qt/core/tests/test_style_dialog.py
glue_qt/dialogs/__init__.py
glue_qt-0.4.0.dist-info/licenses/LICENSE
glue_qt-0.4.0.dist-info/METADATA
glue_qt-0.4.0.dist-info/WHEEL
glue_qt-0.4.0.dist-info/entry_points.txt
glue_qt-0.4.0.dist-info/top_level.txt
glue_qt-0.4.0.dist-info/RECORD
