Metadata-Version: 2.4
Name: glue-qt
Version: 0.4.0
Summary: Multidimensional data visualization across files
Author: Chris Beaumont
Author-email: Thomas Robitaille <glueviz@gmail.com>
Project-URL: Homepage, http://glueviz.org
Classifier: Intended Audience :: Science/Research
Classifier: Operating System :: OS Independent
Classifier: Programming Language :: Python
Classifier: Programming Language :: Python :: 3
Classifier: Programming Language :: Python :: 3.8
Classifier: Programming Language :: Python :: 3.9
Classifier: Programming Language :: Python :: 3.10
Classifier: Programming Language :: Python :: 3.11
Classifier: Programming Language :: Python :: 3.12
Classifier: Programming Language :: Python :: 3.13
Classifier: Topic :: Scientific/Engineering :: Visualization
Classifier: License :: OSI Approved :: BSD License
Requires-Python: >=3.8
License-File: LICENSE
Requires-Dist: glue-core>=1.15.0
Requires-Dist: numpy>=1.17
Requires-Dist: matplotlib>=3.2
Requires-Dist: scipy>=1.1
Requires-Dist: echo>=0.6
Requires-Dist: astropy>=4.0
Requires-Dist: setuptools>=30.3.0
Requires-Dist: qtpy>=1.9
Requires-Dist: ipython<9.0,>=4.0
Requires-Dist: ipykernel!=5.0.0,!=5.1.0,>=4.0
Requires-Dist: qtconsole!=5.4.2,>=4.3
Requires-Dist: pvextractor>=0.2
Requires-Dist: importlib_resources>=1.3; python_version < "3.9"
Requires-Dist: importlib_metadata>=3.6; python_version < "3.10"
Provides-Extra: docs
Requires-Dist: sphinx<7; extra == "docs"
Requires-Dist: sphinx-automodapi; extra == "docs"
Requires-Dist: sphinxcontrib-spelling; extra == "docs"
Requires-Dist: numpydoc; extra == "docs"
Requires-Dist: sphinx-book-theme; extra == "docs"
Provides-Extra: qt
Requires-Dist: PyQt5>=5.14; extra == "qt"
Provides-Extra: test
Requires-Dist: pytest; extra == "test"
Requires-Dist: pytest-cov; extra == "test"
Requires-Dist: pytest-faulthandler; extra == "test"
Requires-Dist: pytest-flake8; extra == "test"
Requires-Dist: objgraph; extra == "test"
Dynamic: license-file
